qec/__init__.py
qec/code_constructions/__init__.py
qec/code_constructions/css_code.py
qec/code_constructions/hgp_code.py
qec/code_constructions/periodic_surface_xzzx.py
qec/code_constructions/rotated_xzzx.py
qec/code_constructions/stabilizer_code.py
qec/code_constructions/surface_code.py
qec/code_constructions/toric_code.py
qec/code_instances/__init__.py
qec/code_instances/five_qubit_code.py
qec/code_instances/saved_codes/1.json
qec/code_instances/saved_codes/2.json
qec/code_instances/saved_codes/3.json
qec/code_instances/saved_codes/4.json
qec/codetables_de/__init__.py
qec/codetables_de/codetables_de.py
qec/utils/__init__.py
qec/utils/binary_pauli_utils.py
qec/utils/codetables_de_utils.py
qec/utils/load_code_util.py
qec/utils/sparse_binary_utils.py
qec-0.3.3.dist-info/licenses/LICENSE
qec-0.3.3.dist-info/METADATA
qec-0.3.3.dist-info/WHEEL
qec-0.3.3.dist-info/top_level.txt
qec-0.3.3.dist-info/RECORD
