Metadata-Version: 2.4
Name: qec
Version: 0.3.3
Summary: Python Tools for Quantum Error Correction
Author-email: Joschka Roffe <joschka@roffe.eu>, Tamas Noszko <T.K.Noszko@sms.ed.ac.uk>, Liam Veeder-Sweeney <L.D.Veeder-Sweeney@sms.ed.ac.uk>
License: MIT License
Classifier: Development Status :: 4 - Beta
Requires-Python: >=3.9
License-File: LICENSE
Requires-Dist: ldpc>=2.2.7
Requires-Dist: numpy>=1.24.0
Requires-Dist: scipy>=1.9.3
Requires-Dist: requests
Requires-Dist: beautifulsoup4
Dynamic: license-file
